{"cameraMode":{"drawMode":0,"name":"Shaded","section":"Shading Mode"},"sceneLighting":true,"audioPlay":false,"sceneViewState":{"m_AlwaysRefresh":false,"showFog":true,"showSkybox":true,"showFlares":true,"showImageEffects":true,"showParticleSystems":true,"showVisualEffectGraphs":true,"m_FxEnabled":true},"in2DMode":false,"pivot":{"x":-5.15343713760376,"y":7.471712112426758,"z":-0.13270992040634156},"rotation":{"x":-0.06550027430057526,"y":-0.6937429308891296,"z":0.06415020674467087,"w":-0.7145311236381531},"size":1.3364524841308594,"orthographic":false}